bygg/__init__.py
bygg/logutils.py
bygg/main.py
bygg/py.typed
bygg/system_helpers.py
bygg/util.py
bygg/cmd/argument_parsing.py
bygg/cmd/argument_unparsing.py
bygg/cmd/build_clean.py
bygg/cmd/completions.py
bygg/cmd/configuration.py
bygg/cmd/datastructures.py
bygg/cmd/dispatcher.py
bygg/cmd/environments.py
bygg/cmd/list_actions.py
bygg/cmd/maintenance.py
bygg/cmd/tree.py
bygg/cmd/watch.py
bygg/core/action.py
bygg/core/cache.py
bygg/core/common_types.py
bygg/core/dag.py
bygg/core/digest.py
bygg/core/job.py
bygg/core/runner.py
bygg/core/scaffolding.py
bygg/core/scheduler.py
bygg/output/job_output.py
bygg/output/output.py
bygg/output/status_display.py
bygg-0.12.0.dist-info/METADATA
bygg-0.12.0.dist-info/WHEEL
bygg-0.12.0.dist-info/entry_points.txt
bygg-0.12.0.dist-info/licenses/LICENSE
bygg-0.12.0.dist-info/RECORD
