Metadata-Version: 2.4
Name: bygg
Version: 0.12.0
Summary: A small build system
Project-URL: Homepage, https://github.com/rikardg/bygg
Project-URL: Bug Tracker, https://github.com/rikardg/bygg/issues
Author-email: Rikard Gillemyr <rikard.gillemyr@gmail.com>
License: MIT License
License-File: LICENSE
Classifier: Environment :: Console
Classifier: Framework :: Pytest
Classifier: Intended Audience :: Developers
Classifier: License :: OSI Approved :: MIT License
Classifier: Operating System :: OS Independent
Classifier: Programming Language :: Python :: 3
Classifier: Topic :: Software Development :: Build Tools
Classifier: Typing :: Typed
Requires-Python: >=3.11
Requires-Dist: argcomplete>=3.6.2
Requires-Dist: dacite>=1.9.2
Requires-Dist: dc-schema>=0.0.8
Requires-Dist: dill>=0.4.0
Requires-Dist: loky>=3.5.5
Requires-Dist: watchdog>=6.0.0
